decmopy/__init__.py
decmopy/decmo/__init__.py
decmopy/decmo/decmo_float.py
decmopy/decmo/decmo_integ.py
decmopy/decmo2/__init__.py
decmopy/decmo2/crec.py
decmopy/decmo2/decmo2.py
decmopy/decmo2/dgen.py
decmopy/decmo2/drec.py
decmopy-1.0.0.dist-info/LICENSE
decmopy-1.0.0.dist-info/METADATA
decmopy-1.0.0.dist-info/WHEEL
decmopy-1.0.0.dist-info/top_level.txt
decmopy-1.0.0.dist-info/RECORD
