Metadata-Version: 2.1
Name: decmopy
Version: 1.0.0
Summary: Python implementation of DECMO algorithms inside the JMetalPy framework
Home-page: https://github.com/xetxezarreta/decmopy
Author: Xabier Etxezarreta
License-File: LICENSE
Requires-Dist: jmetalpy (==1.5.5)
